tapita/Hack-Font-License.md
tapita/HackNerdFont-Regular.ttf
tapita/__init__.py
tapita/__main__.py
tapita-0.1.0.dist-info/LICENSE.md
tapita-0.1.0.dist-info/METADATA
tapita-0.1.0.dist-info/WHEEL
tapita-0.1.0.dist-info/entry_points.txt
tapita-0.1.0.dist-info/RECORD
