Metadata-Version: 2.1
Name: tapita
Version: 0.1.0
Summary: A tool/library to automatically create book covers
Home-page: https://github.com/ralsina/tapita
License: MIT
Keywords: ebook,cover
Author: Roberto Alsina
Author-email: roberto.alsina@gmail.com
Requires-Python: >=3.7,<4.0
Classifier: License :: OSI Approved :: MIT License
Classifier: Programming Language :: Python :: 3
Classifier: Programming Language :: Python :: 3.7
Classifier: Programming Language :: Python :: 3.8
Classifier: Programming Language :: Python :: 3.9
Classifier: Programming Language :: Python :: 3.10
Classifier: Programming Language :: Python :: 3.11
Requires-Dist: Pillow (>=9.5.0,<10.0.0)
Requires-Dist: click (>=8.1.3,<9.0.0)
Project-URL: Repository, https://github.com/ralsina/tapita
